{"type":"FeatureCollection","features":[{"type":"Feature","geometry":{"type":"Point","coordinates":[106.12281520976563,9.254220150390623]},"properties":{"name":"Thành phố Cần Thơ","name_en":"Cần Thơ"}},{"type":"Feature","geometry":{"type":"Point","coordinates":[104.7855405222656,10.020698856640623]},"properties":{"name":"Tỉnh An Giang","name_en":"An Giang Province"}},{"type":"Feature","geometry":{"type":"Point","coordinates":[107.0297389832031,17.095405780078128]},"properties":{"name":"Tỉnh Quảng Trị","name_en":"Quảng Trị Province"}},{"type":"Feature","geometry":{"type":"Point","coordinates":[105.7401940703125,21.027171579687497]},"properties":{"name":"Thành phố Hà Nội","name_en":"Hà Nội"}},{"type":"Feature","geometry":{"type":"Point","coordinates":[107.52518242265626,9.587158872656245]},"properties":{"name":"Thành phố Hồ Chí Minh","name_en":"Ho Chi Minh City"}},{"type":"Feature","geometry":{"type":"Point","coordinates":[106.3916637390625,22.636672954687498]},"properties":{"name":"Tỉnh Cao Bằng","name_en":"Cao Bằng Province"}},{"type":"Feature","geometry":{"type":"Point","coordinates":[104.94629520039062,8.845638945703126]},"properties":{"name":"Tỉnh Cà Mau","name_en":"Cà Mau Province"}},{"type":"Feature","geometry":{"type":"Point","coordinates":[105.76873245546876,10.41651914140625]},"properties":{"name":"Tỉnh Đồng Tháp","name_en":"Đồng Tháp Province"}},{"type":"Feature","geometry":{"type":"Point","coordinates":[106.54338689296873,9.872652669531249]},"properties":{"name":"Tỉnh Vĩnh Long","name_en":"Vĩnh Long Province"}},{"type":"Feature","geometry":{"type":"Point","coordinates":[108.87112889687499,14.096404446875]},"properties":{"name":"Tỉnh Gia Lai","name_en":"Gia Lai Province"}},{"type":"Feature","geometry":{"type":"Point","coordinates":[108.34155186601559,12.682122612890625]},"properties":{"name":"Tỉnh Đắk Lắk","name_en":"Đắk Lắk Province"}},{"type":"Feature","geometry":{"type":"Point","coordinates":[108.59136765996094,10.471632284179691]},"properties":{"name":"Tỉnh Lâm Đồng","name_en":"Lâm Đồng Province"}},{"type":"Feature","geometry":{"type":"Point","coordinates":[109.11997572265625,11.89134067265625]},"properties":{"name":"Tỉnh Khánh Hòa","name_en":"Khánh Hòa Province"}},{"type":"Feature","geometry":{"type":"Point","coordinates":[109.00218307773439,15.090271424609375]},"properties":{"name":"Tỉnh Quảng Ngãi","name_en":"Quảng Ngãi Province"}},{"type":"Feature","geometry":{"type":"Point","coordinates":[108.38293316093751,15.7885082578125]},"properties":{"name":"Thành phố Đà Nẵng","name_en":"Đà Nẵng"}},{"type":"Feature","geometry":{"type":"Point","coordinates":[107.71875504921874,16.548563291406246]},"properties":{"name":"Thành phố Huế","name_en":"Huế"}},{"type":"Feature","geometry":{"type":"Point","coordinates":[106.08813616015625,18.41198351640625]},"properties":{"name":"Tỉnh Hà Tĩnh","name_en":"Hà Tĩnh Province"}},{"type":"Feature","geometry":{"type":"Point","coordinates":[104.89991546289063,19.24890898085938]},"properties":{"name":"Tỉnh Nghệ An","name_en":"Nghệ An Province"}},{"type":"Feature","geometry":{"type":"Point","coordinates":[105.6094564015625,19.8302788796875]},"properties":{"name":"Tỉnh Thanh Hóa","name_en":"Thanh Hóa Province"}},{"type":"Feature","geometry":{"type":"Point","coordinates":[106.13841624414063,11.490717160546877]},"properties":{"name":"Tỉnh Tây Ninh","name_en":"Tây Ninh Province"}},{"type":"Feature","geometry":{"type":"Point","coordinates":[106.38537591640625,19.971844885156255]},"properties":{"name":"Tỉnh Ninh Bình","name_en":"Ninh Bình Province"}},{"type":"Feature","geometry":{"type":"Point","coordinates":[106.71982701757811,20.356832063671877]},"properties":{"name":"Tỉnh Hưng Yên","name_en":"Hưng Yên Province"}},{"type":"Feature","geometry":{"type":"Point","coordinates":[106.94643712343752,20.625206148437503]},"properties":{"name":"Thành phố Hải Phòng","name_en":"Hải Phòng"}},{"type":"Feature","geometry":{"type":"Point","coordinates":[106.67608932890626,21.364522889843744]},"properties":{"name":"Tỉnh Bắc Ninh","name_en":"Bắc Ninh Province"}},{"type":"Feature","geometry":{"type":"Point","coordinates":[105.2949819125,20.7534629625]},"properties":{"name":"Tỉnh Phú Thọ","name_en":"Phú Thọ Province"}},{"type":"Feature","geometry":{"type":"Point","coordinates":[107.64280245703127,21.15303378359375]},"properties":{"name":"Tỉnh Quảng Ninh","name_en":"Quảng Ninh Province"}},{"type":"Feature","geometry":{"type":"Point","coordinates":[105.80718815000002,22.186980050000003]},"properties":{"name":"Tỉnh Thái Nguyên","name_en":"Thái Nguyên Province"}},{"type":"Feature","geometry":{"type":"Point","coordinates":[103.8386112546875,21.2904659171875]},"properties":{"name":"Tỉnh Sơn La","name_en":"Sơn La Province"}},{"type":"Feature","geometry":{"type":"Point","coordinates":[103.33823838867187,22.386579548046875]},"properties":{"name":"Tỉnh Lai Châu","name_en":"Lai Châu Province"}},{"type":"Feature","geometry":{"type":"Point","coordinates":[103.26347878632812,21.71677322851562]},"properties":{"name":"Tỉnh Điện Biên","name_en":"Điện Biên Province"}},{"type":"Feature","geometry":{"type":"Point","coordinates":[104.62121161562501,21.848074503124998]},"properties":{"name":"Tỉnh Lào Cai","name_en":"Lào Cai Province"}},{"type":"Feature","geometry":{"type":"Point","coordinates":[105.0255734890625,22.544311623437494]},"properties":{"name":"Tỉnh Tuyên Quang","name_en":"Tuyên Quang Province"}},{"type":"Feature","geometry":{"type":"Point","coordinates":[106.96739654453125,11.75455753515625]},"properties":{"name":"Tỉnh Đồng Nai","name_en":"Đồng Nai Province"}},{"type":"Feature","geometry":{"type":"Point","coordinates":[106.41052726132811,21.95100682460938]},"properties":{"name":"Tỉnh Lạng Sơn","name_en":"Lạng Sơn Province"}}]}